jetburn-3.2.0.dist-info/top_level.txt
jetburn-3.2.0.dist-info/entry_points.txt
jetburn-3.2.0.dist-info/RECORD
jetburn-3.2.0.dist-info/METADATA
jetburn-3.2.0.dist-info/LICENSE
jetburn-3.2.0.dist-info/WHEEL
jetburn-3.2.0.dist-info/AUTHORS.rst
jetburn/search_results_parser.cpython-36m-i386-linux-gnu.so
jetburn/atc.cpython-36m-i386-linux-gnu.so
jetburn/__init__.cpython-36m-i386-linux-gnu.so
jetburn/settings.cpython-36m-i386-linux-gnu.so
jetburn/app.cpython-36m-i386-linux-gnu.so
jetburn/questions.cpython-36m-i386-linux-gnu.so
jetburn/utils.cpython-36m-i386-linux-gnu.so
jetburn/operations.cpython-36m-i386-linux-gnu.so
jetburn/__init__.py
jetburn/__version__.cpython-36m-i386-linux-gnu.so
